hipypi/__init__.py
hipypi/_dev_version.py
hipypi/_version.py
hipypi/main.py
hipypi/version.py
hipyi-0.1.4.dist-info/METADATA
hipyi-0.1.4.dist-info/WHEEL
hipyi-0.1.4.dist-info/top_level.txt
hipyi-0.1.4.dist-info/RECORD
